notebookManagerPackageNT/__init__.py
notebookManagerPackageNT/notebook_manager.py
notebookManagerPackageNT-0.4.dist-info/METADATA
notebookManagerPackageNT-0.4.dist-info/WHEEL
notebookManagerPackageNT-0.4.dist-info/top_level.txt
notebookManagerPackageNT-0.4.dist-info/RECORD
